jirareport/__init__.py
jirareport/__main__.py
jirareport/retriever.py
jirareport/writer.py
jirareport-0.0.1.dist-info/METADATA
jirareport-0.0.1.dist-info/WHEEL
jirareport-0.0.1.dist-info/top_level.txt
jirareport-0.0.1.dist-info/RECORD
