Metadata-Version: 2.1
Name: jirareport
Version: 0.0.1
Summary: Commands to allow command line jira reports.
Home-page: https://github.com/magmax/jirareport
Author: Miguel Ángel García
Author-email: miguelangel.garcia@gmail.com
License: MIT
Keywords: jira atlassian report
Platform: UNKNOWN
Classifier: Development Status :: 5 - Production/Stable
Classifier: Programming Language :: Python :: 3.6
Classifier: Programming Language :: Python :: 3.7
Classifier: Programming Language :: Python :: 3.8
Classifier: Environment :: Console
Classifier: License :: OSI Approved :: MIT License
Classifier: Operating System :: OS Independent
Requires-Dist: jira (==2.0.0)
Requires-Dist: pyyaml (==5.2)
